{"info":{"title":"113701_2016.346","author":"martyjc","creator":"PScript5.dll Version 5.2.2","producer":"Acrobat Distiller 6.0.1 (Windows)","creationdate":1418390615000,"moddate":1418390615000,"tagged":"no","form":"none","pages":1,"encrypted":"no","page_size":"595 x 842 pts (A4)","page_rot":0,"mediabox":"0.00     0.00   595.00   842.00","cropbox":"0.00     0.00   595.00   842.00","bleedbox":"0.00     0.00   595.00   842.00","trimbox":"0.00     0.00   595.00   842.00","artbox":"0.00     0.00   595.00   842.00","file_size":"21923 bytes","optimized":"yes","pdf_version":1.4},"data":"STA® - UNICALIBRATOR                                                                                                                                                                                        REF 00675\n\n\n\nBbFfBfcBbF bFcBb FfBc bBFfBcFfBb Bc fBbFbBcbB fFcBb FfBc bB fFcBb BfFcBfbB FcBfBbFBcFbB fBcbB fFcFbBfbBc bB FfBc fBb FcBbFfBfc          Code Réactif\n                                                                                                                                                                                                                  113701\n\nA+113701006750916A                                                                                                                                                                                                 12350\n                                                                                                                                        Reagent Code\n\nBbFfBfcBb BfFcBb FfBc bB FfBcbBfBbFcFfBb BcFbB fBc bB fFcBb FfBcbB fFcBb BfFcBb BfFcFbBfbBc fBb FcFfBb Bc bBFfBcbB fFcBfB bFc           Paramètre                         Coffret                         Taux\n                                                                                                                                                                                                                  2016-09\n\nA0112350100096310B\n                                                                                                                                        Parameter                          Kit                            Level\n\n\nBbFfBfcBb FfBcbB FfBc bB fFcBb BfFcBb BfFcFbBfBbcBb FfBc bBFfBcbB FfBc bBfbFcBb FfBc bB fFcBbF BfBc bB fFcFbBfBb cBbFbBfcBfB bFc\n                                                                                                                                                                  ®                 ®\n                                                                                                                                                              STA - Néoplastine CI                         100         %\n                                                                                                                                        TP\n                                                                                                                                        PT                       ®             ®\nA1100091112104094B                                                                                                                                            STA - Néoplastine CI Plus                    96          %\n\n\nBbFfBfcBb fBbFcBb BfFcFbBf bBcfFbB cBb FfBc bBfBbFcBb FfBc bB fFcFbBfBb cFbBf bBcbB FfBc bB fFcBb FfBc bB FfBc bBf bFcBb BfFcBfB bFc\n                                                                                                                                                                 ®                 ®\n                                                                                                                                        Fibrinogen(e)         STA - Fibrinogen, STA - Fib*                 310      mg/dl\n                                                                                                                                                                  ®\n                                                                                                                                        Facteur               STA - Deficient II,\n                                                                                                                                                     II          ®\n                                                                                                                                                                                                           100         %\nA2098121099101120B                                                                                                                      Factor                STA - ImmunoDef II*\n                                                                                                                                        Facteur                  ®\n                                                                                                                                                     V                                                     91          %\nBbFfBfcFfBb BcbB fFcFbBf bBcbBfBbFcBb FfBc bB fFcFbBfbBc bBFfBcbB fFcFbBf bBcbB FfBc bB FfBcFfBb Bc bB FfBc bB fFcFfBb Bc fB bFc\n                                                                                                                                                              STA - Deficient V\n                                                                                                                                        Factor\n                                                                                                                                        Facteur                  ®\n                                                                                                                                                     VII      STA - Deficient VII                          112         %\nA3092109109113103B                                                                                                                      Factor\n                                                                                                                                        Facteur\n                                                                                                                                                     X        STA® - Deficient X                           104         %\n\nBbFfBfcBbFBfBcbB FfBc bB FfBcbB fFcFfBb Bc bB FfBc bB fFcBb BfFcFbBfBb cBfBb FcBb FfBc bBfbFcBbfBbFcBfBbFBc bBf bFcBfBfBbFc\n                                                                                                                                        Factor\n                                                                                                                                        Facteur                  ®\n                                                                                                                                                     XII      STA - ImmunoDef XII*                         94          %\n                                                                                                                                        Factor\nA411031009612272B\n                                                                                                                                        Facteur                  ®\n                                                                                                                                                     VIII     STA - Deficient VIII                         98          %\n                                                                                                                                        Factor\n                                                                                                                                        Facteur                  ®\n                                                                                                                                                     IX       STA - Deficient IX                           121         %\n                                                                                                                                        Factor\n                                                                                                                                        Facteur                  ®\n                                                                                                                                                     XI       STA - Deficient XI                           99          %\n                                                                                                                                        Factor\n                                                                                                                                        Facteur                  ®\n                                                                                                                                                     XII      STA - Deficient XII                          101         %\n                                                                                                                                        Factor\n                                                                                                                                                                 ®         ®\n                                                                                                                                        Protein(e) C          STA - Staclot Protein C                      120         %\n                                                                                                                                                                  ®         ®\n                                                                                                                                        Protein(e) S          STA - Staclot Protein S                      92          %\n\n                                                                                                                                        AT                    STA® - Stachrom ® AT III                     109         %\n                                                                                                                                                                  ®             ®\n                                                                                                                                        Protein(e) C          STA - Stachrom Protein C                     109         %\n\n                                                                                                                                        Antiplasmin(e)        STA® - Stachrom ® Antiplasmin                113         %\n\n                                                                                                                                        Plasminogen(e)        STA® - Stachrom ® Plasminogen                103         %\n                                                                                                                                        TP d'Owren               ®\n                                                                                                                                                              STA - Hepato-Prest*                          110         %\n                                                                                                                                        Owren's PT\n                                                                                                                                        Fibrinogen(e)         STA® - Liquid Fib*                           310      mg/dl\n                                                                                                                                        Facteur\n                                                                                                                                                 VIII         STA® - ImmunoDef VIII*                        96         %\n                                                                                                                                        Factor\n                                                                                                                                        Facteur                   ®\n                                                                                                                                                 IX           STA - ImmunoDef IX*                           122        %\n                                                                                                                                        Factor\n                                                                                                                                       * Non disponible aux Etats-Unis / Not available in the United States\n\n\n\n\n                                                                                                                                       26345 07 - 2013.02\n\f","decode":[{"i":{"kitCode":"00675","kitLot":"113701","kitExpiry":"0916","productsCount":1,"productCodes":["12350"],"parametersCount":22,"parameters":["100","96","310","100","91","112","104","94","98","121","99","101","120","92","109","109","113","103","110","310","96","122"]}}]}