{"info":{"title":"113561_2017.104","author":"martyjc","creator":"PScript5.dll Version 5.2.2","producer":"Acrobat Distiller 6.0.1 (Windows)","creationdate":1429013374000,"moddate":1429013374000,"tagged":"no","form":"none","pages":1,"encrypted":"no","page_size":"595 x 842 pts (A4)","page_rot":0,"mediabox":"0.00     0.00   595.00   842.00","cropbox":"0.00     0.00   595.00   842.00","bleedbox":"0.00     0.00   595.00   842.00","trimbox":"0.00     0.00   595.00   842.00","artbox":"0.00     0.00   595.00   842.00","file_size":"22277 bytes","optimized":"yes","pdf_version":1.4},"data":"STA® - UNICALIBRATOR                                                                                                                                                                                                                              REF 00675\n\n\n\nBbFfB cFbB fBc bB FfBc bB FfBcFfBb BcFbB fBc fBb FcBb FfBc bB fFcBb BfFcBf bB FcBf bF BcFbB fBc bB fFcBb FfBc bB FfBc fBbF Bc fB bFc                                           Code Réactif\n                                                                                                                                                                                                                                                         113561\n\nA5113561006750117B                                                                                                                                                                                                                                        12350\n                                                                                                                                                                               Reagent Code\n\n\nBbFfB cBf bB FcBb FfBc bB FfBc bBfbFcFfBb BcFbB fBc bB fFcBb FfBc bB fFcFfBb Bc bB FfBc bB fFcBb BfFcFfBb Bc bF Bf cFbB fBc fB bFc                                             Paramètre                         Coffret                         Taux\n                                                                                                                                                                                                                                                         2017-01\n\nA6112350103100345B\n                                                                                                                                                                               Parameter                          Kit                            Level\n\n\nBbFfB cBf bF Bc bB FfBc bB fFcFfBb Bc bB fFcFbBf bBcFbBf bBc bB FfBc bBf bFcBb FfBc bB FfBc bB fFcBf bF Bc bB fFcFbBf bBc fBbF Bc fB bFc                                       TP\n                                                                                                                                                                               PT\n                                                                                                                                                                                                     STA® - Néoplastine ® CI                      103         %\n\nA7103099121107097B                                                                                                                                                                                   STA® - Néoplastine ® CI Plus                 100         %\n\n                                                                                                                                                                                                     STA® - Fibrinogen, STA ® - Fib*\nBbFfB cBfFbB cBb FfBc bB FfBc fFbB cBb FfBcFfBb Bc bF Bf cBb FfBc bB fFcFbB fBc bB FfBc bB fFcBf bF Bc bBFfBc bBf bFcBb FfBc fB bFc\n                                                                                                                                                                               Fibrinogen(e)                                                      345      mg/dl\n                                                                                                                                                                                                         ®\n                                                                                                                                                                               Facteur               STA - Deficient II,\n                                                                                                                                                                                            II                                                    103         %\nA8118134105107121B                                                                                                                                                             Factor                STA® - ImmunoDef II*\n                                                                                                                                                                               Facteur\n                                                                                                                                                                                            V        STA® - Deficient V                           99          %\n\nBbF f B c F bBf bBc bB f F c F bBf bBc f Bb F c Bb F f Bc bB f F c Bf F bB c Bb F f Bc bB F f Bc bBf bF c Bb F f Bc bB F f Bc bF Bf c Bb F f Bc bB f F c Bf bB F c Bf BbF c\n                                                                                                                                                                               Factor\n                                                                                                                                                                               Facteur\n                                                                                                                                                                                            VII      STA® - Deficient VII                         121         %\n                                                                                                                                                                               Factor\nA9096108112114106B\n                                                                                                                                                                               Facteur\n                                                                                                                                                                                            X        STA® - Deficient X                           107         %\n                                                                                                                                                                               Factor\nBbFfB cBbFfBb cBb FfBc bB FfBc fBbF BcFfBb Bc bF Bf cFbB fBc bB FfBc bB FfBc fBbF Bc bB FfBcFfBb Bc bB fFcBb FfBc bB fFcBb fBbFcBf BbFc                                        Facteur\n                                                                                                                                                                               Factor\n                                                                                                                                                                                            XII      STA® - ImmunoDef XII*                        97          %\nA$117345117130102B                                                                                                                                                             Facteur\n                                                                                                                                                                                            VIII     STA® - Deficient VIII                        118         %\n                                                                                                                                                                               Factor\n\nBbF f B c Bb f F bBc bF Bf c F bB f Bc f B bF c                                                                                                                                Facteur\n                                                                                                                                                                               Factor\n                                                                                                                                                                                            IX       STA® - Deficient IX                          134         %\nA-45B                                                                                                                                                                          Facteur\n                                                                                                                                                                                            XI       STA® - Deficient XI                          105         %\n                                                                                                                                                                               Factor\n                                                                                                                                                                               Facteur\n                                                                                                                                                                                            XII      STA® - Deficient XII                         107         %\n                                                                                                                                                                               Factor\n                                                                                                                                                                               Protein(e) C          STA® - Staclot® Protein C                    121         %\n\n                                                                                                                                                                               Protein(e) S          STA® - Staclot® Protein S                    96          %\n\n                                                                                                                                                                               AT                    STA® - Stachrom ® AT III                     108         %\n\n                                                                                                                                                                               Protein(e) C          STA® - Stachrom ® Protein C                  112         %\n                                                                                                                                                                                                         ®            ®\n                                                                                                                                                                               Antiplasmin(e)        STA - Stachrom Antiplasmin                   114         %\n\n                                                                                                                                                                               Plasminogen(e)        STA® - Stachrom ® Plasminogen                106         %\n                                                                                                                                                                               TP d'Owren\n                                                                                                                                                                               Owren's PT            STA® - Hepato-Prest*                         117         %\n\n                                                                                                                                                                               Fibrinogen(e)         STA® - Liquid Fib*                           345      mg/dl\n                                                                                                                                                                               Facteur\n                                                                                                                                                                                        VIII         STA® - ImmunoDef VIII*                        117        %\n                                                                                                                                                                               Factor\n                                                                                                                                                                               Facteur\n                                                                                                                                                                                        IX           STA® - ImmunoDef IX*                          130        %\n                                                                                                                                                                               Factor\n                                                                                                                                                                               Facteur\n                                                                                                                                                                                        XI           STA® - ImmunoDef XI*                          102        %\n                                                                                                                                                                               Factor\n                                                                                                                                                                              * Non disponible aux Etats-Unis / Not available in the United States\n\n\n\n\n                                                                                                                                                                              26345 08 - 2014.01\n\f","decode":[{"i":{"kitCode":"00675","kitLot":"113561","kitExpiry":"0117","productsCount":1,"productCodes":["12350"],"parametersCount":23,"parameters":["103","100","345","103","99","121","107","97","118","134","105","107","121","96","108","112","114","106","117","345","117","130","102"]}}]}